urlshortner/__init__.py
urlshortner/admin.py
urlshortner/apps.py
urlshortner/models.py
urlshortner/tests.py
urlshortner/urls.py
urlshortner/views.py
urlshortner/migrations/0001_initial.py
urlshortner/migrations/__init__.py
urlshortner/utils/__init__.py
urlshortner/utils/http_.py
urlshortner/utils/urls.py
django_urlshortner-0.0.2.dist-info/LICENSE
django_urlshortner-0.0.2.dist-info/METADATA
django_urlshortner-0.0.2.dist-info/WHEEL
django_urlshortner-0.0.2.dist-info/top_level.txt
django_urlshortner-0.0.2.dist-info/RECORD
