Metadata-Version: 2.1
Name: django-urlshortner
Version: 0.0.2
Summary: A Django app that provides utils to build a custom URL shortener.
Home-page: https://github.com/jim-junior/django-urlshortner
Author: Beingana Jim Junior
Author-email: jimjunior854@gmail.com
License: MIT
Keywords: django,urlshortener,web
Classifier: Environment :: Web Environment
Classifier: Framework :: Django
Classifier: Intended Audience :: Developers
Classifier: License :: OSI Approved :: BSD License
Classifier: Operating System :: OS Independent
Classifier: Programming Language :: Python
Classifier: Programming Language :: Python :: 3
Classifier: Topic :: Internet :: WWW/HTTP
Classifier: Topic :: Internet :: WWW/HTTP :: Dynamic Content
Requires-Python: >=3.6
License-File: LICENSE
Requires-Dist: Django (>=3.0)
